Metadata-Version: 2.1
Name: osszex
Version: 1.0
Summary: package manager.
Home-page: UNKNOWN
Author: helper
License: MIT
Keywords: style
Platform: UNKNOWN
Classifier: Development Status :: 5 - Production/Stable
